odoo/addons/mrp_bom_line_net_qty/README.rst
odoo/addons/mrp_bom_line_net_qty/__init__.py
odoo/addons/mrp_bom_line_net_qty/__manifest__.py
odoo/addons/mrp_bom_line_net_qty/i18n/fr.po
odoo/addons/mrp_bom_line_net_qty/i18n/it.po
odoo/addons/mrp_bom_line_net_qty/i18n/mrp_bom_line_net_qty.pot
odoo/addons/mrp_bom_line_net_qty/models/__init__.py
odoo/addons/mrp_bom_line_net_qty/models/mrp_bom_line.py
odoo/addons/mrp_bom_line_net_qty/readme/CONTRIBUTORS.rst
odoo/addons/mrp_bom_line_net_qty/readme/DESCRIPTION.rst
odoo/addons/mrp_bom_line_net_qty/static/description/change_net_qty_after.png
odoo/addons/mrp_bom_line_net_qty/static/description/change_net_qty_before.png
odoo/addons/mrp_bom_line_net_qty/static/description/icon.png
odoo/addons/mrp_bom_line_net_qty/static/description/index.html
odoo/addons/mrp_bom_line_net_qty/static/description/mrp_bom_line_net_qty.gif
odoo/addons/mrp_bom_line_net_qty/tests/__init__.py
odoo/addons/mrp_bom_line_net_qty/tests/test_mrp_bom_line_net_qty.py
odoo/addons/mrp_bom_line_net_qty/views/view_mrp_bom.xml
odoo_addon_mrp_bom_line_net_qty-16.0.1.0.0.6.dist-info/METADATA
odoo_addon_mrp_bom_line_net_qty-16.0.1.0.0.6.dist-info/WHEEL
odoo_addon_mrp_bom_line_net_qty-16.0.1.0.0.6.dist-info/top_level.txt
odoo_addon_mrp_bom_line_net_qty-16.0.1.0.0.6.dist-info/RECORD
